<?xml version="1.0" encoding="UTF-8"?>
<udm.DeploymentPackage version="2.0" application="LongRunningApp">
    <application/>
    <orchestrator>
        <value>sequential-by-dependency</value>
    </orchestrator>
    <satisfiesReleaseNotes>false</satisfiesReleaseNotes>
    <deployables>
        <yak.YakLongRunningTask name="/step1">
            <tags/>
        </yak.YakLongRunningTask>
        <yak.YakLongRunningTask name="/step2">
            <tags/>
        </yak.YakLongRunningTask>
    </deployables>
    <applicationDependencies>
        <entry key="GrazingApp">[2.0,2.0]</entry>
    </applicationDependencies>
    <dependencyResolution>LATEST</dependencyResolution>
    <undeployDependencies>false</undeployDependencies>
</udm.DeploymentPackage>
